nacla/__init__.py
nacla/nacla.py
nacla/model/rnn.pth
nacla-0.0.20.dist-info/METADATA
nacla-0.0.20.dist-info/WHEEL
nacla-0.0.20.dist-info/top_level.txt
nacla-0.0.20.dist-info/RECORD
